halem/Base_functions.py
halem/Calc_path.py
halem/Functions.py
halem/Functions_old.py
halem/Mesh_maker.py
halem/__init__.py
halem/particle_tracking.py
halem/simulation.py
halem-0.3.1.dist-info/LICENSE.txt
halem-0.3.1.dist-info/METADATA
halem-0.3.1.dist-info/WHEEL
halem-0.3.1.dist-info/top_level.txt
halem-0.3.1.dist-info/RECORD
