Metadata-Version: 2.1
Name: halem
Version: 0.3.1
Summary: The Route optimization for dynamic flow field searches the optimal route for a given flow field.
Home-page: https://github.com/TUDelft-CITG/Route_optimization_in_dynamic_currents
Author: Pieter van Halem
Author-email: pieter.vanhalem@vanoord.com
License: mit
Keywords: Route Optimization in Dynamic Flow Fields
Platform: any
Classifier: Programming Language :: Python :: 3
Classifier: License :: OSI Approved :: MIT License
Classifier: Operating System :: OS Independent
Requires-Dist: numpy
Requires-Dist: networkx
Requires-Dist: shapely
Requires-Dist: scipy
Requires-Dist: netCDF4
Requires-Dist: matplotlib
Requires-Dist: IPython
Requires-Dist: geopy
Requires-Dist: pyproj
Requires-Dist: sphinx-rtd-theme
Requires-Dist: simplekml
Provides-Extra: testing
Requires-Dist: pytest ; extra == 'testing'
Requires-Dist: pytest-cov ; extra == 'testing'
Requires-Dist: pytest-timeout ; extra == 'testing'
